LICENSE.txt
MANIFEST.in
README.md
VERSION
setup.py
docs/index.md
hitchkey/__init__.py
hitchkey/commandline.py
hitchkey/languagestrings.py
hitchkey/utils.py
hitchkey.egg-info/PKG-INFO
hitchkey.egg-info/SOURCES.txt
hitchkey.egg-info/dependency_links.txt
hitchkey.egg-info/entry_points.txt
hitchkey.egg-info/not-zip-safe
hitchkey.egg-info/top_level.txt